{
    "store_button_stack@start.stacked_row": {
        "controls": [
            {
                "store_button@start.store_button": {
                    "enabled": "(not $store_disabled and not ($is_ios and $pre_release)))",
                    "bindings": [
                        {
                            "binding_name": "(not #marketplace_disabled)",
                            "binding_name_override": "#visible"
                        }
                    ]
                }
            },
            {
                "update_icon@start.update_prompt_icon": {
                    "ignored": "$store_disabled",
                    "size": [
                        "52.38%y",
                        15
                    ],
                    "offset": [
                        -16,
                        -6
                    ],
                    "bindings": [
                        {
                            "binding_name": "#update_icon_visible",
                            "binding_name_override": "#visible",
                            "binding_condition": "always"
                        }
                    ]
                }
            },
            {
                "new_offers_icon@start.new_offers_icon": {
                    "ignored": "$store_disabled",
                    "offset": [
                        8,
                        -6
                    ],
                    "anchor_from": "top_right",
                    "anchor_to": "top_right",
                    "bindings": [
                        {
                            "binding_name": "#new_offers",
                            "binding_name_override": "#visible"
                        }
                    ]
                }
            },
            {
                "marketplace_error_button@common_buttons.dynamic_tooltip_notification_panel": {
                    "size": [
                        "100%",
                        "100%"
                    ],
                    "button_mappings": [
                        {
                            "from_button_id": "button.menu_select",
                            "to_button_id": "button.menu_store_error",
                            "mapping_type": "pressed"
                        },
                        {
                            "to_button_id": "button.is_hovered",
                            "mapping_type": "pressed"
                        }
                    ],
                    "consume_hover_events": false,
                    "focus_enabled": true,
                    "$dynamic_tooltip_button_visibility_binding_name": "#has_marketplace_errors",
                    "$tooltip_popup_visible_binding": "#marketplace_errors_tooltip_visible",
                    "$override_tooltip_popup_image": true,
                    "$tooltip_popup_override_image_panel": "start.store_error_image",
                    "$tooltip_text_binding_name": "#marketplace_error_text",
                    "$tool_tip_text_max_size": [
                        "300px",
                        "default"
                    ],
                    "$tooltip_panel_content": "start.store_error_content",
                    "bindings": [
                        {
                            "binding_name": "#marketplace_disabled",
                            "binding_name_override": "#visible"
                        }
                    ]
                }
            },
            {
                "marketplace_error_icon@start.marketplace_error_icon": {
                    "anchor_from": "top_left",
                    "anchor_to": "top_left",
                    "offset": [
                        -2,
                        0
                    ],
                    "bindings": [
                        {
                            "binding_name": "#marketplace_disabled",
                            "binding_name_override": "#visible"
                        }
                    ]
                }
            }
        ]
    }
}