{
  "AnimatedCampfireItems": "Aesthetic",
  "AllayElytra": "Aesthetic",
  "HoneySlime": "Colorful Slime",
  "WhiteSlime": "Colorful Slime",
  "LightGraySlime": "Colorful Slime",
  "GraySlime": "Colorful Slime",
  "BlackSlime": "Colorful Slime",
  "BrownSlime": "Colorful Slime",
  "RedSlime": "Colorful Slime",
  "OrangeSlime": "Colorful Slime",
  "YellowSlime": "Colorful Slime",
  "GreenSlime": "Colorful Slime",
  "CyanSlime": "Colorful Slime",
  "LightBlueSlime": "Colorful Slime",
  "BlueSlime": "Colorful Slime",
  "PurpleSlime": "Colorful Slime",
  "MagentaSlime": "Colorful Slime",
  "PinkSlime": "Colorful Slime",
  "RainbowSlime": "Colorful Slime",
  "MonochromeSlime": "Colorful Slime",
  "UpdatedObserverTexture": "Fixes and Consistency",
  "RedstoneWireFix": "Fixes and Consistency",
  "BigDripleafStemFix": "Fixes and Consistency",
  "SmallDripleafStemFix": "Fixes and Consistency",
  "ConsistentBlankDecoratedPot": "Fixes and Consistency",
  "ConsistentBuckets": "Fixes and Consistency",
  "ConsistentTadpoleBucket": "Fixes and Consistency",
  "CactusBottomFix": "Fixes and Consistency",
  "ConsistentBambooPlanks": "Fixes and Consistency",
  "AccurateScaffolding": "Fixes and Consistency",
  "ConsistentHelmets": "Fixes and Consistency",
  "BrighterRibArmorTrim": "Fixes and Consistency",
  "HangingSignLogs": "Fixes and Consistency",
  "SoulSoilSoulCampfire": "Fixes and Consistency",
  "Blaze'sRodsFix": "Fixes and Consistency",
  "NicerFastLeaves": "Fixes and Consistency",
  "ConsistentSmoothStone": "Fixes and Consistency",
  "DoubleSlabFix": "Fixes and Consistency",
  "HoeFix": "Fixes and Consistency",
  "PixelConsistentBat": "Fixes and Consistency",
  "PixelConsistentGhast": "Fixes and Consistency",
  "PixelConsistentElderGuardian": "Fixes and Consistency",
  "PixelConsistentWither": "Fixes and Consistency",
  "PixelConsistentSigns": "Fixes and Consistency",
  "PixelConsistentExperienceOrbs": "Fixes and Consistency",
  "PixelConsistentBeaconBeam": "Fixes and Consistency",
  "PixelConsistentSonicBoom": "Fixes and Consistency",
  "PixelConsistentGuardianBeam": "Fixes and Consistency",
  "SmileyAxolotls": "Fun",
  "GreenAxolotl": "Fun",
  "Beeralis": "Fun",
  "SusSandandGravel": "Fun",
  "XisumaTurtle": "Fun",
  "XisumaSquids": "Fun",
  "WanderingXisuma": "Fun",
  "DarthXisumaPiglins": "Fun",
  "TechnobladePigs": "Fun",
  "StrideyStriders": "Fun",
  "EmeraldstoRubies": "Fun",
  "WitherBee": "Fun",
  "ilmangoGoldenApples": "Fun",
  "EnglishEnchantingTable": "Fun",
  "StandardGalacticAlphabet": "Fun",
  "BaconBeam": "Fun",
  "PhantomRain": "Fun",
  "WHAT": "Fun",
  "UselessSpyglass": "Fun",
  "ScreamingGoatsMeme": "Fun",
  "IwishItCouldBeChristmasEveryday": "Fun",
  "NumberedHotbar": "HUD and GUI",
  "NoCrosshair": "HUD and GUI",
  "SmallerCrosshair": "HUD and GUI",
  "DotCrosshair": "HUD and GUI",
  "PlusDotCrosshair": "HUD and GUI",
  "CircleCrosshair": "HUD and GUI",
  "CircleDotCrosshair": "HUD and GUI",
  "SquareCrosshair": "HUD and GUI",
  "SquareDotCrosshair": "HUD and GUI",
  "SquarePlusCrosshair": "HUD and GUI",
  "SquarePlusDotCrosshair": "HUD and GUI",
  "4AngledCrosshair": "HUD and GUI",
  "4AngledDotCrosshair": "HUD and GUI",
  "HeartCrosshair": "HUD and GUI",
  "ArrowCrosshair": "HUD and GUI",
  "WitherHearts": "HUD and GUI",
  "RainbowExperienceBar": "HUD and GUI",
  "SmootherFont": "HUD and GUI",
  "DarkUI": "HUD and GUI",
  "TransparentUI": "HUD and GUI",
  "HighContrastUI": "HUD and GUI",
  "BedrockEditionSubtitle": "HUD and GUI",
  "SteveZombies": "More Zombies",
  "AlexZombies": "More Zombies",
  "AriZombies": "More Zombies",
  "EfeZombies": "More Zombies",
  "KaiZombies": "More Zombies",
  "MakenaZombies": "More Zombies",
  "NoorZombies": "More Zombies",
  "SunnyZombies": "More Zombies",
  "ZuriZombies": "More Zombies",
  "AllZombies": "More Zombies",
  "Classic": "Menu Panoramas",
  "Ocean": "Menu Panoramas",
  "Village": "Menu Panoramas",
  "Bees": "Menu Panoramas",
  "Nether": "Menu Panoramas",
  "AmethystGeode": "Menu Panoramas",
  "SunsetValley": "Menu Panoramas",
  "MangroveSwamp": "Menu Panoramas",
  "TheEnd": "Menu Panoramas",
  "pack.png": "Menu Panoramas",
  "Nostalgia": "Menu Panoramas",
  "OceansideExtremeHills": "Menu Panoramas",
  "LakesideSunset": "Menu Panoramas",
  "UndergroundLavaPool": "Menu Panoramas",
  "TU69TutorialWorld": "Menu Panoramas",
  "Stridey'sResourcePackDevelopmentWorld": "Menu Panoramas",
  "Xisuma'sHermitcraftBaseSeason1": "Menu Panoramas",
  "Xisuma'sHermitcraftBaseSeason2": "Menu Panoramas",
  "Xisuma'sHermitcraftBaseSeason3": "Menu Panoramas",
  "Xisuma'sHermitcraftBaseSeason4": "Menu Panoramas",
  "Xisuma'sHermitcraftBaseSeason5": "Menu Panoramas",
  "Xisuma'sHermitcraftBaseSeason6": "Menu Panoramas",
  "Xisuma'sHermitcraftBaseSeason7": "Menu Panoramas",
  "Xisuma'sHermitcraftBaseSeason8": "Menu Panoramas",
  "Xisuma'sHermitcraftBaseSeason9": "Menu Panoramas",
  "JavaBoom": "Parity",
  "JavaMap": "Parity",
  "JavaEnderDragonBall": "Parity",
  "DungeonsCreepers": "Parity",
  "DungeonsDirt": "Parity",
  "DungeonsStone": "Parity",
  "DungeonsTerracotta": "Parity",
  "SuperSmashBrosEnderman": "Parity",
  "JavaDriedKelp": "Parity",
  "LegacyConsoleEmerald": "Parity",
  "LegacyConsoleSnowball": "Parity",
  "QuieterAllays": "Peace and Quiet",
  "QuieterAxolotls": "Peace and Quiet",
  "QuieterBats": "Peace and Quiet",
  "QuieterBees": "Peace and Quiet",
  "QuieterBlazes": "Peace and Quiet",
  "QuieterCamels": "Peace and Quiet",
  "QuieterChickens": "Peace and Quiet",
  "QuieterDolphins": "Peace and Quiet",
  "QuieterEnderDragon": "Peace and Quiet",
  "QuieterEndermen": "Peace and Quiet",
  "QuieterGoats": "Peace and Quiet",
  "QuieterGuardians": "Peace and Quiet",
  "QuieterHoglins": "Peace and Quiet",
  "QuieterHorses": "Peace and Quiet",
  "QuieterIllagers": "Peace and Quiet",
  "QuieterIronGolems": "Peace and Quiet",
  "QuieterLlamas": "Peace and Quiet",
  "QuieterPandas": "Peace and Quiet",
  "QuieterParrots": "Peace and Quiet",
  "QuieterPhantoms": "Peace and Quiet",
  "QuieterPigs": "Peace and Quiet",
  "QuieterPiglins": "Peace and Quiet",
  "QuieterPolarBears": "Peace and Quiet",
  "QuieterRabbits": "Peace and Quiet",
  "QuieterRavagers": "Peace and Quiet",
  "QuieterSheep": "Peace and Quiet",
  "QuieterShulkers": "Peace and Quiet",
  "QuieterSilverfish": "Peace and Quiet",
  "QuieterSkeletons": "Peace and Quiet",
  "QuieterSlimes": "Peace and Quiet",
  "QuieterSniffers": "Peace and Quiet",
  "QuieterSnowGolems": "Peace and Quiet",
  "QuieterSpiders": "Peace and Quiet",
  "QuieterSquids": "Peace and Quiet",
  "QuieterStriders": "Peace and Quiet",
  "QuieterTadpoles": "Peace and Quiet",
  "QuieterTurtles": "Peace and Quiet",
  "QuieterVexes": "Peace and Quiet",
  "QuieterVillagers": "Peace and Quiet",
  "QuieterWardens": "Peace and Quiet",
  "QuieterWitches": "Peace and Quiet",
  "QuieterWither": "Peace and Quiet",
  "QuieterWolves": "Peace and Quiet",
  "QuieterZombies": "Peace and Quiet",
  "QuieterRain": "Peace and Quiet",
  "QuieterThunder": "Peace and Quiet",
  "QuieterExplosions": "Peace and Quiet",
  "QuieterDispensersandDroppers": "Peace and Quiet",
  "QuieterMinecarts": "Peace and Quiet",
  "QuieterFire": "Peace and Quiet",
  "QuieterNetherPortals": "Peace and Quiet",
  "QuieterWater": "Peace and Quiet",
  "QuieterConsumables": "Peace and Quiet",
  "QuieterSculkSensors": "Peace and Quiet",
  "QuieterSculkShriekers": "Peace and Quiet",
  "QuieterPistons": "Peace and Quiet",
  "NoCaveSounds": "Peace and Quiet",
  "ClassicMinecraftLogo": "Retro",
  "AlphaMinecraftLogo": "Retro",
  "DirtBackground": "Retro",
  "ClassicOres": "Retro",
  "OldCobblestone": "Retro",
  "Pre1.18StrippedDarkOak": "Retro",
  "OldPlanks": "Retro",
  "OldGravel": "Retro",
  "OldNetherrack": "Retro",
  "OldLava": "Retro",
  "OldObsidian": "Retro",
  "OldMetalBlocks": "Retro",
  "OldWater": "Retro",
  "OldIce": "Retro",
  "OldLapis": "Retro",
  "OldSponge": "Retro",
  "OldWoolColors": "Retro",
  "OnlyBedIcons": "Retro",
  "OldShulkerColors": "Retro",
  "PoppytoRose": "Retro",
  "RenameTerracottatoHardenedClay": "Retro",
  "RenameDirtPathtoGrassPath": "Retro",
  "RenamePotterySherdtoPotteryShard": "Retro",
  "ZombiePigman": "Retro",
  "OarlessBoats": "Retro",
  "OldDoorSound": "Retro",
  "OldDamageSound": "Retro",
  "OldExplosionSound": "Retro",
  "OldLevelUpSound": "Retro",
  "GoldenSavanna": "Terrain",
  "3DFungi": "Terrain",
  "UnobstrusiveRain": "Unobstrusive",
  "UnobstrusiveSnow": "Unobstrusive",
  "UnobstrusiveParticles": "Unobstrusive",
  "NoCherryLeavesParticles": "Unobstrusive",
  "BorderlessGlass": "Unobstrusive",
  "BorderlessStainedGlass": "Unobstrusive",
  "BorderlessTintedGlass": "Unobstrusive",
  "CleanGlass": "Unobstrusive",
  "CleanStainedGlass": "Unobstrusive",
  "CleanTintedGlass": "Unobstrusive",
  "UnobstrusiveScaffolding": "Unobstrusive",
  "UnobstrusiveEnchantmentGlint": "Unobstrusive",
  "LowerFire": "Unobstrusive",
  "LowerShield": "Unobstrusive",
  "NoFog": "Unobstrusive",
  "TranslucentPumpkinOverlay": "Unobstrusive",
  "NoPumpkinOverlay": "Unobstrusive",
  "TranslucentSpyglassOverlay": "Unobstrusive",
  "NoSpyglassOverlay": "Unobstrusive",
  "NoVignette": "Unobstrusive",
  "NoBeaconBeam": "Unobstrusive",
  "InvisibleTotem": "Unobstrusive",
  "SmallerUtilities": "Unobstrusive",
  "ShorterSwords": "Unobstrusive",
  "OreBorders": "Utility",
  "SusSandGravelBorders": "Utility",
  "BuddingAmethystBorders": "Utility",
  "InfestedStoneItems": "Utility",
  "InfestedStoneBlocks": "Utility",
  "WaxedCopperItems": "Utility",
  "WaxedCopperBlocks": "Utility",
  "ShinyAgedAmethystCluster": "Utility",
  "DifferentStems": "Utility",
  "Age25Kelp": "Utility",
  "MineProgressBar": "Utility",
  "ClearBannerPatterns": "Utility",
  "HungerPreview": "Utility",
  "MusicDiscRedstoneLevelPreview": "Utility",
  "StickyPistonSides": "Utility",
  "DirectionalHoppers": "Utility",
  "DirectionalDispensersandDroppers": "Utility",
  "DirectionalObservers": "Utility",
  "CleanRedstoneDust": "Utility",
  "UnlitRedstoneOre": "Utility",
  "VisibleTripwires": "Utility",
  "TotemShield": "Utility",
  "CompassLodestone": "Utility",
  "BrewingGuide": "Utility",
  "VisualHoneyStage": "Utility",
  "VisualNoteBlockPitchParticle": "Utility",
  "ArabicNumerals": "Utility",
  "VariatedCoarseDirt": "Variation",
  "VariatedVillagers": "Variation"
}